timeserio/RELEASE-VERSION
timeserio/__init__.py
timeserio/externals.py
timeserio/ini.py
timeserio/version.py
timeserio/batches/__init__.py
timeserio/batches/utils.py
timeserio/batches/chunked/__init__.py
timeserio/batches/chunked/base.py
timeserio/batches/chunked/dask.py
timeserio/batches/chunked/pandas.py
timeserio/batches/chunked/parquet.py
timeserio/batches/single/__init__.py
timeserio/batches/single/base.py
timeserio/batches/single/row.py
timeserio/batches/single/sequence.py
timeserio/data/__init__.py
timeserio/data/datasets.py
timeserio/data/mock.py
timeserio/keras/__init__.py
timeserio/keras/batches.py
timeserio/keras/callbacks.py
timeserio/keras/multinetwork.py
timeserio/keras/timing.py
timeserio/keras/utils.py
timeserio/model_selection/__init__.py
timeserio/model_selection/time_series_split.py
timeserio/multimodel/__init__.py
timeserio/multimodel/base.py
timeserio/multimodel/pipegen.py
timeserio/pipeline/__init__.py
timeserio/pipeline/multipipeline.py
timeserio/pipeline/pipeline.py
timeserio/preprocessing/__init__.py
timeserio/preprocessing/aggregate.py
timeserio/preprocessing/base.py
timeserio/preprocessing/batches.py
timeserio/preprocessing/datetime.py
timeserio/preprocessing/encoding.py
timeserio/preprocessing/multipipeline.py
timeserio/preprocessing/pandas.py
timeserio/preprocessing/utils.py
timeserio/utils/__init__.py
timeserio/utils/functools.py
timeserio/utils/pickle.py
timeserio/validation/__init__.py
timeserio/validation/validation.py
timeserio-0.10.4.dist-info/LICENSE.txt
timeserio-0.10.4.dist-info/METADATA
timeserio-0.10.4.dist-info/WHEEL
timeserio-0.10.4.dist-info/entry_points.txt
timeserio-0.10.4.dist-info/top_level.txt
timeserio-0.10.4.dist-info/RECORD
