Metadata-Version: 2.1
Name: timeserio
Version: 0.10.4
Summary: Machine Learning and Forecasting tools
Home-page: https://github.com/octoenergy/timeserio
Author: Octopus Energy
Author-email: nerds@octopus.energy
License: MIT
Platform: UNKNOWN
Classifier: Development Status :: 3 - Alpha
Classifier: Intended Audience :: Developers
Classifier: License :: OSI Approved :: MIT License
Classifier: Operating System :: OS Independent
Classifier: Programming Language :: Python
Classifier: Programming Language :: Python :: 3
Classifier: Programming Language :: Python :: 3.6
Requires-Dist: joblib
Requires-Dist: numpy
Requires-Dist: pandas
Requires-Dist: scikit-learn (==0.20.3)
Requires-Dist: s3fs
Requires-Dist: holidays
